Rich Club/Rich Club.py
Rich Club/__init__.py
richclub/__init__.py
richclub/richclub.py
richclubv2-1.0.0.dev1.dist-info/DESCRIPTION.rst
richclubv2-1.0.0.dev1.dist-info/METADATA
richclubv2-1.0.0.dev1.dist-info/RECORD
richclubv2-1.0.0.dev1.dist-info/WHEEL
richclubv2-1.0.0.dev1.dist-info/metadata.json
richclubv2-1.0.0.dev1.dist-info/top_level.txt
